hp/__init__.py
hp/console.py
hp/wikipedia.py
myhp-0.1.0.dist-info/METADATA
myhp-0.1.0.dist-info/WHEEL
myhp-0.1.0.dist-info/entry_points.txt
myhp-0.1.0.dist-info/licenses/LICENSE
myhp-0.1.0.dist-info/RECORD
