Metadata-Version: 2.4
Name: myhp
Version: 0.1.0
Summary: 
License-File: LICENSE
Author: Joans
Author-email: joans@example.com
Requires-Python: >=3.11,<4.0
Classifier: Programming Language :: Python :: 3
Classifier: Programming Language :: Python :: 3.11
Classifier: Programming Language :: Python :: 3.12
Classifier: Programming Language :: Python :: 3.13
Classifier: Programming Language :: Python :: 3.14
Requires-Dist: click (>=8.3.0,<9.0.0)
Requires-Dist: desert (>=2022.9.22,<2023.0.0)
Requires-Dist: marshmallow (>=4.1.0,<5.0.0)
Requires-Dist: requests (>=2.32.5,<3.0.0)
